contactcenter/__init__.py
contactcenter/core.py
contactcenter/contact/__init__.py
contactcenter/contact/data.py
contactcenter/contact/persistence.py
contactcenter/contact/services.py
contactcenter/queues/__init__.py
contactcenter/queues/persistence.py
contactcenter/queues/services.py
contactcenter/trace/__init__.py
contactcenter/trace/persistence.py
contactcenter/trace/services.py
socom_contactcenter_backend-0.0.1.dev2.dist-info/LICENSE.txt
socom_contactcenter_backend-0.0.1.dev2.dist-info/METADATA
socom_contactcenter_backend-0.0.1.dev2.dist-info/WHEEL
socom_contactcenter_backend-0.0.1.dev2.dist-info/top_level.txt
socom_contactcenter_backend-0.0.1.dev2.dist-info/RECORD
